Workbook

Sheet Income
A1: Income Category | B1: Monthly Amount | C1: Annual Amount
A2: Salary | B2: 5000 | C2: =B2*12
A3: Freelance Income | B3: 1200 | C3: =B3*12
A4: Investment Returns | B4: 500 | C4: =B4*12
A5: Rental Income | B5: 800 | C5: =B5*12
A6: Other Income | B6: 200 | C6: =B6*12
A7: Total Income | B7: =SUM(B2:B6) | C7: =SUM(C2:C6)

Sheet Expenses
A1: Expense Category | B1: Budgeted | C1: Actual | D1: Difference | E1: % of Budget
A2: Housing (Rent/Mortgage) | B2: 1500 | C2: 1500 | D2: =B2-C2 | E2: =IF(B2=0,0,C2/B2)
A3: Utilities | B3: 200 | C3: 185 | D3: =B3-C3 | E3: =IF(B3=0,0,C3/B3)
A4: Groceries | B4: 600 | C4: 650 | D4: =B4-C4 | E4: =IF(B4=0,0,C4/B4)
A5: Transportation | B5: 400 | C5: 420 | D5: =B5-C5 | E5: =IF(B5=0,0,C5/B5)
A6: Insurance | B6: 300 | C6: 300 | D6: =B6-C6 | E6: =IF(B6=0,0,C6/B6)
A7: Healthcare | B7: 250 | C7: 180 | D7: =B7-C7 | E7: =IF(B7=0,0,C7/B7)
A8: Entertainment | B8: 300 | C8: 350 | D8: =B8-C8 | E8: =IF(B8=0,0,C8/B8)
A9: Dining Out | B9: 250 | C9: 280 | D9: =B9-C9 | E9: =IF(B9=0,0,C9/B9)
A10: Clothing | B10: 150 | C10: 120 | D10: =B10-C10 | E10: =IF(B10=0,0,C10/B10)
A11: Personal Care | B11: 100 | C11: 95 | D11: =B11-C11 | E11: =IF(B11=0,0,C11/B11)
A12: Education | B12: 200 | C12: 200 | D12: =B12-C12 | E12: =IF(B12=0,0,C12/B12)
A13: Savings | B13: 1000 | C13: 1000 | D13: =B13-C13 | E13: =IF(B13=0,0,C13/B13)
... A15: Miscellaneous | B15: 200 | C15: 175 | D15: =B15-C15 | E15: =IF(B15=0,0,C15/B15)
A16: Total Expenses | B16: =SUM(B2:B15) | C16: =SUM(C2:C15) | D16: =SUM(D2:D15) | E16: =IF(B16=0,0,C16/B16)

Sheet Summary
A1: Financial Summary Dashboard
A3: Total Monthly Income | B3: =Income!B7
A4: Total Annual Income | B4: =Income!C7
A6: Total Budgeted Expenses | B6: =Expenses!B16
A7: Total Actual Expenses | B7: =Expenses!C16
A9: Net Income (Budget) | B9: =B3-B6
A10: Net Income (Actual) | B10: =B3-B7
A12: Savings Rate | B12: =IF(B3=0,0,(B3-B7)/B3)
A14: Budget Performance
A15: Over/Under Budget | B15: =Expenses!D16
A16: Budget Adherence | B16: =IF(B6=0,0,B7/B6)
